Workbook
Name Slicer_brand_name: #N/A
Name Slicer_product_category: #N/A

Sheet Cleaned_data
A1: product_name | B1: brand_name | C1: rating | D1: rating_count | E1: marked_price | F1: discounted_price | G1: sizes | H1: product_category | I1: product_id | J1: revenue | K1: discount %
A2: Pure Georgette Bandhani Saree | B2: Mitera | C2: 3.6 | D2: 5 | E2: 6727 | F2: 1681 | G2: Onesize | H2: sarees | I2: 17141476 | J2: =D2*F2 -> 8405 | K2: =((Table4[[#This Row],[marked_price]]-Table4[[#This Row],[discounted_price]])/Table4[[#This Row],[marked_price]])*100 -> 75.011149
A3: Men Accessory Gift Set | B3: WildHorn | C3: 4.5 | D3: 80 | E3: 2999 | F3: 1049 | G3: Onesize | H3: accessory-gift-set | I3: 1410357 | J3: =D3*F3 -> 83920 | K3: =((Table4[[#This Row],[marked_price]]-Table4[[#This Row],[discounted_price]])/Table4[[#This Row],[marked_price]])*100 -> 65.021674
A4: Self-Design Thermal Set | B4: Kanvin | C4: 4.6 | D4: 42 | E4: 1598 | F4: 1278 | G4: S,M,L,XL,XXL | H4: thermal-set | I4: 2223155 | J4: =D4*F4 -> 53676 | K4: =((Table4[[#This Row],[marked_price]]-Table4[[#This Row],[discounted_price]])/Table4[[#This Row],[marked_price]])*100 -> 20.025031
A5: Men Slim Fit T-shirt | B5: Jack & Jones | C5: 3.7 | D5: 7 | E5: 1299 | F5: 649 | G5: S,M,L,XL,XXL | H5: tshirts | I5: 15430520 | J5: =D5*F5 -> 4543 | K5: =((Table4[[#This Row],[marked_price]]-Table4[[#This Row],[discounted_price]])/Table4[[#This Row],[marked_price]])*100 -> 50.038491
A6: Outdoor Rapid-Dry Jacket | B6: HRX by Hrithik Roshan | C6: 4.4 | D6: 186 | E6: 2799 | F6: 1679 | G6: XS,S,M,L,XL | H6: jackets | I6: 11953112 | J6: =D6*F6 -> 312294 | K6: =((Table4[[#This Row],[marked_price]]-Table4[[#This Row],[discounted_price]])/Table4[[#This Row],[marked_price]])*100 -> 40.014291
A7: Floral Maxi Dress | B7: Nayo | C7: 4 | D7: 7 | E7: 1999 | F7: 799 | G7: S,M,L,XL,XXL | H7: dresses | I7: 17634118 | J7: =D7*F7 -> 5593 | K7: =((Table4[[#This Row],[marked_price]]-Table4[[#This Row],[discounted_price]])/Table4[[#This Row],[marked_price]])*100 -> 60.030015
A8: Women Ribbed Fitted Top | B8: DressBerry | C8: 4.2 | D8: 252 | E8: 999 | F8: 399 | G8: XS,S,M,L,XL | H8: tops | I8: 11003624 | J8: =D8*F8 -> 100548 | K8: =((Table4[[#This Row],[marked_price]]-Table4[[#This Row],[discounted_price]])/Table4[[#This Row],[marked_price]])*100 -> 60.06006
A9: Men Gold-Toned Brooch | B9: Alvaro Castagnino | C9: 4.9 | D9: 10 | E9: 999 | F9: 399 | G9: Onesize | H9: brooch | I9: 17426638 | J9: =D9*F9 -> 3990 | K9: =((Table4[[#This Row],[marked_price]]-Table4[[#This Row],[discounted_price]])/Table4[[#This Row],[marked_price]])*100 -> 60.06006
A10: Printed Lounge T-shirt | B10: ETC | C10: 4.3 | D10: 52 | E10: 499 | F10: 324 | G10: S,M,L,XL | H10: lounge-tshirts | I10: 12442110 | J10: =D10*F10 -> 16848 | K10: =((Table4[[#This Row],[marked_price]]-Table4[[#This Row],[discounted_price]])/Table4[[#This Row],[marked_price]])*100 -> 35.07014
A11: Men Solid Sliders | B11: Power | C11: 3.9 | D11: 34 | E11: 746 | F11: 671 | G11: UK6,UK7,UK8,UK9,UK10,UK11 | H11: flip-flops | I11: 12453854 | J11: =D11*F11 -> 22814 | K11: =((Table4[[#This Row],[marked_price]]-Table4[[#This Row],[discounted_price]])/Table4[[#This Row],[marked_price]])*100 -> 10.053619
A12: Women Skinny Fit Jeans | B12: Mast & Harbour | C12: 4 | D12: 105 | E12: 1799 | F12: 809 | G12: 26,28,30,32,34,36 | H12: jeans | I12: 12310178 | J12: =D12*F12 -> 84945 | K12: =((Table4[[#This Row],[marked_price]]-Table4[[#This Row],[discounted_price]])/Table4[[#This Row],[marked_price]])*100 -> 55.030573
A13: Unisex Round Sunglasses | B13: WROGN | C13: 4.1 | D13: 338 | E13: 2899 | F13: 1884 | G13: M | H13: sunglasses | I13: 2385219 | J13: =D13*F13 -> 636792 | K13: =((Table4[[#This Row],[marked_price]]-Table4[[#This Row],[discounted_price]])/Table4[[#This Row],[marked_price]])*100 -> 35.012073
... A369: Men Analogue Watch | B369: TIMESMITH | C369: 3.9 | D369: 7 | E369: 2499 | F369: 399 | G369: Onesize | H369: watches | I369: 11135920 | J369: =D369*F369 -> 2793 | K369: =((Table4[[#This Row],[marked_price]]-Table4[[#This Row],[discounted_price]])/Table4[[#This Row],[marked_price]])*100 -> 84.033613
A370: Men Leather Formal Belt | B370: United Colors of Benetton | C370: 3.4 | D370: 7 | E370: 2999 | F370: 899 | G370: 34 | H370: belts | I370: 8488829 | J370: =D370*F370 -> 6293 | K370: =((Table4[[#This Row],[marked_price]]-Table4[[#This Row],[discounted_price]])/Table4[[#This Row],[marked_price]])*100 -> 70.023341
A371: Cone Shade Armed Sconces | B371: Homesake | C371: 4.3 | D371: 21 | E371: 3300 | F371: 1199 | G371: Onesize | H371: wall-lamps | I371: 9246303 | J371: =D371*F371 -> 25179 | K371: =((Table4[[#This Row],[marked_price]]-Table4[[#This Row],[discounted_price]])/Table4[[#This Row],[marked_price]])*100 -> 63.666667
A372: Women Slim Fit Regular Trousers | B372: FORCLAZ By Decathlon | C372: 5 | D372: 6 | E372: 2999 | F372: 2579 | G372: 26,28,30,32,34,36 | H372: trousers | I372: 13168086 | J372: =D372*F372 -> 15474 | K372: =((Table4[[#This Row],[marked_price]]-Table4[[#This Row],[discounted_price]])/Table4[[#This Row],[marked_price]])*100 -> 14.004668
A373: Embroidered High-Low Top | B373: Mayra | C373: 3.1 | D373: 36 | E373: 1095 | F373: 459 | G373: S,M,L,XL | H373: tops | I373: 11091590 | J373: =D373*F373 -> 16524 | K373: =((Table4[[#This Row],[marked_price]]-Table4[[#This Row],[discounted_price]])/Table4[[#This Row],[marked_price]])*100 -> 58.082192
A374: Printed Kurta with Palazzos | B374: FABRIC FITOOR | C374: 4.5 | D374: 15 | E374: 4599 | F374: 1057 | G374: S,M,L,XL,XXL,3XL | H374: kurta-sets | I374: 12103850 | J374: =D374*F374 -> 15855 | K374: =((Table4[[#This Row],[marked_price]]-Table4[[#This Row],[discounted_price]])/Table4[[#This Row],[marked_price]])*100 -> 77.016743
A375: Women Yoke Design Kurta with Trousers With Dupatta | B375: Varanga | C375: 1 | D375: 2 | E375: 4999 | F375: 1699 | G375: S,M,L,XL,XXL | H375: kurta-sets | I375: 13983922 | J375: =D375*F375 -> 3398 | K375: =((Table4[[#This Row],[marked_price]]-Table4[[#This Row],[discounted_price]])/Table4[[#This Row],[marked_price]])*100 -> 66.013203
A376: Men Typography Printed T-shirt | B376: HERE&NOW | C376: 3.8 | D376: 5 | E376: 949 | F376: 284 | G376: S,M,L,XL | H376: tshirts | I376: 16260732 | J376: =D376*F376 -> 1420 | K376: =((Table4[[#This Row],[marked_price]]-Table4[[#This Row],[discounted_price]])/Table4[[#This Row],[marked_price]])*100 -> 70.073762
A377: Unisex Anti Theft Backpack | B377: F Gear | C377: 4.5 | D377: 191 | E377: 4995 | F377: 1898 | G377: Onesize | H377: backpacks | I377: 4385679 | J377: =D377*F377 -> 362518 | K377: =((Table4[[#This Row],[marked_price]]-Table4[[#This Row],[discounted_price]])/Table4[[#This Row],[marked_price]])*100 -> 62.002002
A378: Men Solid Kurta with Pyjamas | B378: VASTRAMAY | C378: 4.4 | D378: 43 | E378: 4499 | F378: 2249 | G378: S,M,L,XL,XXL,3XL | H378: kurta-sets | I378: 4369942 | J378: =D378*F378 -> 96707 | K378: =((Table4[[#This Row],[marked_price]]-Table4[[#This Row],[discounted_price]])/Table4[[#This Row],[marked_price]])*100 -> 50.011114
A379: Girls Embroidered Kurta with Palazzos With Dupatta | B379: Biba | C379: 4.1 | D379: 7 | E379: 3299 | F379: 1649 | G379: 9Y,11Y,13Y,15Y | H379: kurta-sets | I379: 14847260 | J379: =D379*F379 -> 11543 | K379: =((Table4[[#This Row],[marked_price]]-Table4[[#This Row],[discounted_price]])/Table4[[#This Row],[marked_price]])*100 -> 50.015156
A380: PU Structured Sling Bag | B380: Exotic | C380: 4.7 | D380: 9 | E380: 2599 | F380: 1074 | G380: S | H380: handbags | I380: 17394202 | J380: =D380*F380 -> 9666 | K380: =((Table4[[#This Row],[marked_price]]-Table4[[#This Row],[discounted_price]])/Table4[[#This Row],[marked_price]])*100 -> 58.676414
A381: AD-Studded Mangalsutra Set | B381: Brandsoon | C381: 5 | D381: 2 | E381: 2528 | F381: 353 | G381: Onesize | H381: mangalsutra | I381: 17403044 | J381: =D381*F381 -> 706 | K381: =((Table4[[#This Row],[marked_price]]-Table4[[#This Row],[discounted_price]])/Table4[[#This Row],[marked_price]])*100 -> 86.036392
A382: Women Embroidered Rozana Kurta | B382: House of Pataudi | C382: 4.2 | D382: 5 | E382: 3199 | F382: 1919 | G382: XS,S,M,L,XL,XXL | H382: kurtas | I382: 13721048 | J382: =D382*F382 -> 9595 | K382: =((Table4[[#This Row],[marked_price]]-Table4[[#This Row],[discounted_price]])/Table4[[#This Row],[marked_price]])*100 -> 40.012504
... A717: Scoop Neck Fitted Top | B717: Miaz Lifestyle | C717: 3.5 | D717: 88 | E717: 999 | F717: 589 | G717: XS,S,M,L,XL,XXL | H717: tops | I717: 15112544 | J717: =D717*F717 -> 51832 | K717: =((Table4[[#This Row],[marked_price]]-Table4[[#This Row],[discounted_price]])/Table4[[#This Row],[marked_price]])*100 -> 41.041041
A718: Slim Fit Casual Shirt | B718: Louis Philippe Jeans | C718: 3.3 | D718: 3 | E718: 2049 | F718: 1229 | G718: 44 | H718: shirts | I718: 14225978 | J718: =D718*F718 -> 3687 | K718: =((Table4[[#This Row],[marked_price]]-Table4[[#This Row],[discounted_price]])/Table4[[#This Row],[marked_price]])*100 -> 40.019522
A719: Girls Layered A-Line Dress | B719: pspeaches | C719: 4.4 | D719: 54 | E719: 1499 | F719: 524 | G719: 2-3Y,3-4Y,4-5Y,5-6Y,6-7Y,7-8Y,8-9Y,9-10Y,10-11Y,11-12Y | H719: dresses | I719: 13882872 | J719: =D719*F719 -> 28296 | K719: =((Table4[[#This Row],[marked_price]]-Table4[[#This Row],[discounted_price]])/Table4[[#This Row],[marked_price]])*100 -> 65.043362
A720: Women Printed Kurta with Palazzos | B720: Moda Rapido | C720: 3.9 | D720: 8 | E720: 4399 | F720: 1099 | G720: XS,S,M,L,XL,XXL | H720: kurta-sets | I720: 14430866 | J720: =D720*F720 -> 8792 | K720: =((Table4[[#This Row],[marked_price]]-Table4[[#This Row],[discounted_price]])/Table4[[#This Row],[marked_price]])*100 -> 75.017049
A721: Suede Block Mules with Buckles | B721: VALIOSAA | C721: 3.5 | D721: 6 | E721: 2499 | F721: 1474 | G721: EURO35,EURO36,EURO37,EURO38,EURO39,EURO40 | H721: heels | I721: 15777288 | J721: =D721*F721 -> 8844 | K721: =((Table4[[#This Row],[marked_price]]-Table4[[#This Row],[discounted_price]])/Table4[[#This Row],[marked_price]])*100 -> 41.016407
A722: Women Floral Embroidered Kurta | B722: KALINI | C722: 2.8 | D722: 5 | E722: 1249 | F722: 399 | G722: M,L,XL,XXL,3XL | H722: kurtas | I722: 17227692 | J722: =D722*F722 -> 1995 | K722: =((Table4[[#This Row],[marked_price]]-Table4[[#This Row],[discounted_price]])/Table4[[#This Row],[marked_price]])*100 -> 68.054444
A723: Women Solid Block Heels | B723: Padvesh | C723: 3.4 | D723: 5 | E723: 1299 | F723: 649 | G723: EURO38,EURO39,EURO40,EURO41,EURO42 | H723: heels | I723: 12826644 | J723: =D723*F723 -> 3245 | K723: =((Table4[[#This Row],[marked_price]]-Table4[[#This Row],[discounted_price]])/Table4[[#This Row],[marked_price]])*100 -> 50.038491
A724: Women Cotton Solid Pullover | B724: MANGO | C724: 4.2 | D724: 9 | E724: 2990 | F724: 1794 | G724: XS,S,M,L | H724: sweaters | I724: 15721508 | J724: =D724*F724 -> 16146 | K724: =((Table4[[#This Row],[marked_price]]-Table4[[#This Row],[discounted_price]])/Table4[[#This Row],[marked_price]])*100 -> 40
A725: Women High Waist Tummy & Thigh Control Seamless Shapewear | B725: SECRETS BY ZEROKAATA | C725: 3.8 | D725: 138 | E725: 1000 | F725: 820 | G725: M,L,XL | H725: shapewear | I725: 13549778 | J725: =D725*F725 -> 113160 | K725: =((Table4[[#This Row],[marked_price]]-Table4[[#This Row],[discounted_price]])/Table4[[#This Row],[marked_price]])*100 -> 18
A726: Geometric Regular Top | B726: Trend Arrest | C726: 4.2 | D726: 9 | E726: 1299 | F726: 480 | G726: XS,S,M,L,XL | H726: tops | I726: 16247900 | J726: =D726*F726 -> 4320 | K726: =((Table4[[#This Row],[marked_price]]-Table4[[#This Row],[discounted_price]])/Table4[[#This Row],[marked_price]])*100 -> 63.048499
A727: Satin Wrap Dress | B727: NEUDIS | C727: 3.6 | D727: 5 | E727: 2199 | F727: 791 | G727: XS,S,M,L,XL | H727: dresses | I727: 16923146 | J727: =D727*F727 -> 3955 | K727: =((Table4[[#This Row],[marked_price]]-Table4[[#This Row],[discounted_price]])/Table4[[#This Row],[marked_price]])*100 -> 64.029104
A728: Men Skinny Fit Jeans | B728: Allen Solly | C728: 3.5 | D728: 2 | E728: 2799 | F728: 1931 | G728: 30,32,34,36,38 | H728: jeans | I728: 14843430 | J728: =D728*F728 -> 3862 | K728: =((Table4[[#This Row],[marked_price]]-Table4[[#This Row],[discounted_price]])/Table4[[#This Row],[marked_price]])*100 -> 31.011075
A729: Men Solid T-shirt | B729: Moda Rapido | C729: 3.3 | D729: 6 | E729: 999 | F729: 519 | G729: S,M,L,XL | H729: tshirts | I729: 15822046 | J729: =D729*F729 -> 3114 | K729: =((Table4[[#This Row],[marked_price]]-Table4[[#This Row],[discounted_price]])/Table4[[#This Row],[marked_price]])*100 -> 48.048048
A730: Women Regular Top | B730: Ajile by Pantaloons | C730: 4.5 | D730: 15 | E730: 399 | F730: 399 | G730: XS,S,M,L,XL,XXL | H730: tops | I730: 15375470 | J730: =D730*F730 -> 5985 | K730: =((Table4[[#This Row],[marked_price]]-Table4[[#This Row],[discounted_price]])/Table4[[#This Row],[marked_price]])*100 -> 0
... A1019: Men Sneakers | B1019: Ajile by Pantaloons | C1019: 4.4 | D1019: 9 | E1019: 1499 | F1019: 1499 | G1019: UK6,UK7,UK8,UK9,UK10 | H1019: casual-shoes | I1019: 16490752 | J1019: =D1019*F1019 -> 13491 | K1019: =((Table4[[#This Row],[marked_price]]-Table4[[#This Row],[discounted_price]])/Table4[[#This Row],[marked_price]])*100 -> 0
A1020: Geometric Stone Finger Ring | B1020: Yellow Chimes | C1020: 4.4 | D1020: 40 | E1020: 1994 | F1020: 602 | G1020: 9 | H1020: ring | I1020: 15175312 | J1020: =D1020*F1020 -> 24080 | K1020: =((Table4[[#This Row],[marked_price]]-Table4[[#This Row],[discounted_price]])/Table4[[#This Row],[marked_price]])*100 -> 69.809428
A1021: Striped High Neck T-shirt | B1021: Campus Sutra | C1021: 3.9 | D1021: 607 | E1021: 1199 | F1021: 719 | G1021: S,M,L,XL | H1021: tshirts | I1021: 10891018 | J1021: =D1021*F1021 -> 436433 | K1021: =((Table4[[#This Row],[marked_price]]-Table4[[#This Row],[discounted_price]])/Table4[[#This Row],[marked_price]])*100 -> 40.033361
A1022: Football Rapid-Dry Tshirts | B1022: HRX by Hrithik Roshan | C1022: 4 | D1022: 10 | E1022: 1199 | F1022: 779 | G1022: S,M,L,XL,XXL | H1022: tshirts | I1022: 15289632 | J1022: =D1022*F1022 -> 7790 | K1022: =((Table4[[#This Row],[marked_price]]-Table4[[#This Row],[discounted_price]])/Table4[[#This Row],[marked_price]])*100 -> 35.029191
A1023: Regular Checked Casual Shirt | B1023: Roadster | C1023: 4.2 | D1023: 69 | E1023: 1699 | F1023: 849 | G1023: 38,40,42,44 | H1023: shirts | I1023: 12947594 | J1023: =D1023*F1023 -> 58581 | K1023: =((Table4[[#This Row],[marked_price]]-Table4[[#This Row],[discounted_price]])/Table4[[#This Row],[marked_price]])*100 -> 50.029429
A1024: Women Skinny Fit Jeans | B1024: DOLCE CRUDO | C1024: 3.9 | D1024: 152 | E1024: 2549 | F1024: 994 | G1024: 26,28,30,32,34 | H1024: jeans | I1024: 11399986 | J1024: =D1024*F1024 -> 151088 | K1024: =((Table4[[#This Row],[marked_price]]-Table4[[#This Row],[discounted_price]])/Table4[[#This Row],[marked_price]])*100 -> 61.004315
A1025: Unisex Carryon Backpack | B1025: HRX by Hrithik Roshan | C1025: 4.1 | D1025: 181 | E1025: 1099 | F1025: 934 | G1025: Onesize | H1025: backpacks | I1025: 11558280 | J1025: =D1025*F1025 -> 169054 | K1025: =((Table4[[#This Row],[marked_price]]-Table4[[#This Row],[discounted_price]])/Table4[[#This Row],[marked_price]])*100 -> 15.013649
A1026: Women Printed T-shirt | B1026: Mast & Harbour | C1026: 4 | D1026: 14 | E1026: 999 | F1026: 299 | G1026: XS,S,M,L,XL | H1026: tshirts | I1026: 13880712 | J1026: =D1026*F1026 -> 4186 | K1026: =((Table4[[#This Row],[marked_price]]-Table4[[#This Row],[discounted_price]])/Table4[[#This Row],[marked_price]])*100 -> 70.07007
A1027: Print Top | B1027: Zivame | C1027: 4.3 | D1027: 8 | E1027: 645 | F1027: 290 | G1027: XXL,3XL,4XL | H1027: tops | I1027: 18056720 | J1027: =D1027*F1027 -> 2320 | K1027: =((Table4[[#This Row],[marked_price]]-Table4[[#This Row],[discounted_price]])/Table4[[#This Row],[marked_price]])*100 -> 55.03876
A1028: Pack of 3 Ankle Length Socks | B1028: Artengo By Decathlon | C1028: 4.5 | D1028: 176 | E1028: 299 | F1028: 272 | G1028: UK5,UK8,UK11 | H1028: socks | I1028: 14462484 | J1028: =D1028*F1028 -> 47872 | K1028: =((Table4[[#This Row],[marked_price]]-Table4[[#This Row],[discounted_price]])/Table4[[#This Row],[marked_price]])*100 -> 9.0301003
A1029: Girls Printed Top With Skirt | B1029: Cutiekins | C1029: 4 | D1029: 47 | E1029: 1999 | F1029: 699 | G1029: 4-5Y,5-6Y,6-7Y,7-8Y,8-9Y,9-10Y,10-11Y | H1029: clothing-set | I1029: 17261676 | J1029: =D1029*F1029 -> 32853 | K1029: =((Table4[[#This Row],[marked_price]]-Table4[[#This Row],[discounted_price]])/Table4[[#This Row],[marked_price]])*100 -> 65.032516
A1030: Striped Polo Collar T-shirt | B1030: WILD WEST | C1030: 4.2 | D1030: 119 | E1030: 1799 | F1030: 575 | G1030: S,M,L,XL,XXL,3XL | H1030: tshirts | I1030: 11577432 | J1030: =D1030*F1030 -> 68425 | K1030: =((Table4[[#This Row],[marked_price]]-Table4[[#This Row],[discounted_price]])/Table4[[#This Row],[marked_price]])*100 -> 68.037799
A1031: Men Textured Formal Oxfords | B1031: INVICTUS | C1031: 3.7 | D1031: 15 | E1031: 3499 | F1031: 1399 | G1031: UK6,UK7,UK8,UK9,UK10 | H1031: formal-shoes | I1031: 15747714 | J1031: =D1031*F1031 -> 20985 | K1031: =((Table4[[#This Row],[marked_price]]-Table4[[#This Row],[discounted_price]])/Table4[[#This Row],[marked_price]])*100 -> 60.017148
A1032: Women Printed Sliders | B1032: Pampy Angel | C1032: 4.3 | D1032: 24 | E1032: 499 | F1032: 394 | G1032: UK4,UK5,UK6,UK7,UK8 | H1032: flip-flops | I1032: 13132308 | J1032: =D1032*F1032 -> 9456 | K1032: =((Table4[[#This Row],[marked_price]]-Table4[[#This Row],[discounted_price]])/Table4[[#This Row],[marked_price]])*100 -> 21.042084
... A2153: Men Clogs | B2153: WALKWAY | C2153: 3.5 | D2153: 6 | E2153: 999 | F2153: 999 | G2153: UK6,UK7,UK8,UK9,UK10,UK11 | H2153: flip-flops | I2153: 17111412 | J2153: =D2153*F2153 -> 5994 | K2153: =((Table4[[#This Row],[marked_price]]-Table4[[#This Row],[discounted_price]])/Table4[[#This Row],[marked_price]])*100 -> 0
A2154: Men Reversible Belt | B2154: Tommy Hilfiger | C2154: 4.7 | D2154: 15 | E2154: 2399 | F2154: 2159 | G2154: 40 | H2154: belts | I2154: 2175290 | J2154: =D2154*F2154 -> 32385 | K2154: =((Table4[[#This Row],[marked_price]]-Table4[[#This Row],[discounted_price]])/Table4[[#This Row],[marked_price]])*100 -> 10.004168
A2155: Men Solid Slim Fit Track Pants | B2155: Sports52 wear | C2155: 3.7 | D2155: 36 | E2155: 995 | F2155: 437 | G2155: M,L,XL,XXL,3XL | H2155: track-pants | I2155: 14190682 | J2155: =D2155*F2155 -> 15732 | K2155: =((Table4[[#This Row],[marked_price]]-Table4[[#This Row],[discounted_price]])/Table4[[#This Row],[marked_price]])*100 -> 56.080402
A2156: Pure Cotton Printed Night suit | B2156: Anubhutee | C2156: 4 | D2156: 358 | E2156: 2849 | F2156: 997 | G2156: S,M,L,XL,XXL | H2156: night-suits | I2156: 13592712 | J2156: =D2156*F2156 -> 356926 | K2156: =((Table4[[#This Row],[marked_price]]-Table4[[#This Row],[discounted_price]])/Table4[[#This Row],[marked_price]])*100 -> 65.005265
A2157: Makeup Remover Cleanser 250 ml | B2157: BIODERMA | C2157: 4.6 | D2157: 48 | E2157: 990 | F2157: 990 | G2157: 100-350 ML | H2157: makeup-remover | I2157: 2052298 | J2157: =D2157*F2157 -> 47520 | K2157: =((Table4[[#This Row],[marked_price]]-Table4[[#This Row],[discounted_price]])/Table4[[#This Row],[marked_price]])*100 -> 0
A2158: Women Pack of 2 Lounge Shorts | B2158: zebu | C2158: 4.3 | D2158: 279 | E2158: 1598 | F2158: 607 | G2158: M,L,XL | H2158: lounge-shorts | I2158: 12253792 | J2158: =D2158*F2158 -> 169353 | K2158: =((Table4[[#This Row],[marked_price]]-Table4[[#This Row],[discounted_price]])/Table4[[#This Row],[marked_price]])*100 -> 62.015019
A2159: Unisex Natreal Face Wash | B2159: Taavi | C2159: 4.2 | D2159: 100 | E2159: 249 | F2159: 136 | G2159: 100-350 ML | H2159: face-wash-and-cleanser | I2159: 13454612 | J2159: =D2159*F2159 -> 13600 | K2159: =((Table4[[#This Row],[marked_price]]-Table4[[#This Row],[discounted_price]])/Table4[[#This Row],[marked_price]])*100 -> 45.381526
A2160: Set of 6 Abstract Printed Chair Cove | B2160: Cortina | C2160: 4 | D2160: 23 | E2160: 4498 | F2160: 1999 | G2160: Onesize | H2160: chair-cover | I2160: 13995836 | J2160: =D2160*F2160 -> 45977 | K2160: =((Table4[[#This Row],[marked_price]]-Table4[[#This Row],[discounted_price]])/Table4[[#This Row],[marked_price]])*100 -> 55.558026
A2161: Women Printed Ballerinas | B2161: ZAPATOZ | C2161: 4 | D2161: 73 | E2161: 999 | F2161: 649 | G2161: EURO36,EURO37,EURO38,EURO39,EURO40,EURO41,EURO42 | H2161: flats | I2161: 14617398 | J2161: =D2161*F2161 -> 47377 | K2161: =((Table4[[#This Row],[marked_price]]-Table4[[#This Row],[discounted_price]])/Table4[[#This Row],[marked_price]])*100 -> 35.035035
A2162: Men Sneakers | B2162: Sparx | C2162: 4.3 | D2162: 48 | E2162: 899 | F2162: 899 | G2162: UK6,UK7,UK8,UK9,UK10 | H2162: casual-shoes | I2162: 10927848 | J2162: =D2162*F2162 -> 43152 | K2162: =((Table4[[#This Row],[marked_price]]-Table4[[#This Row],[discounted_price]])/Table4[[#This Row],[marked_price]])*100 -> 0
A2163: Women Solid Backpack | B2163: DressBerry | C2163: 4.6 | D2163: 61 | E2163: 2899 | F2163: 2319 | G2163: Onesize | H2163: backpacks | I2163: 13350098 | J2163: =D2163*F2163 -> 141459 | K2163: =((Table4[[#This Row],[marked_price]]-Table4[[#This Row],[discounted_price]])/Table4[[#This Row],[marked_price]])*100 -> 20.006899
A2164: Men Valentine watch | B2164: Fastrack | C2164: 4.4 | D2164: 91 | E2164: 2295 | F2164: 2295 | G2164: Onesize | H2164: watches | I2164: 11472384 | J2164: =D2164*F2164 -> 208845 | K2164: =((Table4[[#This Row],[marked_price]]-Table4[[#This Row],[discounted_price]])/Table4[[#This Row],[marked_price]])*100 -> 0
A2165: Printed Slim Fit Casual Shirt | B2165: The Indian Garage Co | C2165: 4.2 | D2165: 30 | E2165: 1749 | F2165: 699 | G2165: 38,40,42,44 | H2165: shirts | I2165: 15000726 | J2165: =D2165*F2165 -> 20970 | K2165: =((Table4[[#This Row],[marked_price]]-Table4[[#This Row],[discounted_price]])/Table4[[#This Row],[marked_price]])*100 -> 60.034305
A2166: Mini Lipstick - All Fired Up | B2166: M.A.C | C2166: 4.6 | D2166: 414 | E2166: 1100 | F2166: 1100 | G2166: Onesize | H2166: lipstick | I2166: 13216192 | J2166: =D2166*F2166 -> 455400 | K2166: =((Table4[[#This Row],[marked_price]]-Table4[[#This Row],[discounted_price]])/Table4[[#This Row],[marked_price]])*100 -> 0
... A2907: Women Typography Printed T-shirt | B2907: Roadster | C2907: 2.3 | D2907: 3 | E2907: 999 | F2907: 349 | G2907: XS,S,M,L,XL | H2907: tshirts | I2907: 16962302 | J2907: =D2907*F2907 -> 1047 | K2907: =((Table4[[#This Row],[marked_price]]-Table4[[#This Row],[discounted_price]])/Table4[[#This Row],[marked_price]])*100 -> 65.065065
A2908: Unisex Printed Leather Belt | B2908: Tommy Hilfiger | C2908: 4.6 | D2908: 18 | E2908: 3399 | F2908: 3399 | G2908: 44 | H2908: belts | I2908: 12071676 | J2908: =D2908*F2908 -> 61182 | K2908: =((Table4[[#This Row],[marked_price]]-Table4[[#This Row],[discounted_price]])/Table4[[#This Row],[marked_price]])*100 -> 0
A2909: Boys Pack of 2 Solid Joggers | B2909: YK | C2909: 4 | D2909: 5 | E2909: 2099 | F2909: 2099 | G2909: 8-9Y,10-11Y,11-12Y,13-14Y | H2909: track-pants | I2909: 15267456 | J2909: =D2909*F2909 -> 10495 | K2909: =((Table4[[#This Row],[marked_price]]-Table4[[#This Row],[discounted_price]])/Table4[[#This Row],[marked_price]])*100 -> 0
A2910: Slim Fit Opaque Casual Shirt | B2910: HIGHLANDER | C2910: 3.8 | D2910: 213 | E2910: 1199 | F2910: 563 | G2910: 39,40,42,44 | H2910: shirts | I2910: 15896542 | J2910: =D2910*F2910 -> 119919 | K2910: =((Table4[[#This Row],[marked_price]]-Table4[[#This Row],[discounted_price]])/Table4[[#This Row],[marked_price]])*100 -> 53.044204
A2911: Women Ankle Length Leggings | B2911: TAG 7 | C2911: 4.1 | D2911: 13 | E2911: 1799 | F2911: 593 | G2911: S,M,L,XL,XXL,3XL | H2911: leggings | I2911: 17706158 | J2911: =D2911*F2911 -> 7709 | K2911: =((Table4[[#This Row],[marked_price]]-Table4[[#This Row],[discounted_price]])/Table4[[#This Row],[marked_price]])*100 -> 67.037243
A2912: Floral Jhumkas Earrings | B2912: SOHI | C2912: 4.3 | D2912: 75 | E2912: 1000 | F2912: 410 | G2912: Onesize | H2912: earrings | I2912: 16974376 | J2912: =D2912*F2912 -> 30750 | K2912: =((Table4[[#This Row],[marked_price]]-Table4[[#This Row],[discounted_price]])/Table4[[#This Row],[marked_price]])*100 -> 59
A2913: Ribbed Jersey Dress | B2913: H&M | C2913: 4.1 | D2913: 8 | E2913: 1299 | F2913: 1299 | G2913: XS,S,M,L,XL | H2913: dresses | I2913: 16530842 | J2913: =D2913*F2913 -> 10392 | K2913: =((Table4[[#This Row],[marked_price]]-Table4[[#This Row],[discounted_price]])/Table4[[#This Row],[marked_price]])*100 -> 0
A2914: Women Solid Lounge Tshirts | B2914: Jockey | C2914: 4.4 | D2914: 87 | E2914: 499 | F2914: 499 | G2914: S,M,L | H2914: lounge-tshirts | I2914: 15039164 | J2914: =D2914*F2914 -> 43413 | K2914: =((Table4[[#This Row],[marked_price]]-Table4[[#This Row],[discounted_price]])/Table4[[#This Row],[marked_price]])*100 -> 0
A2915: Women Cateye Sunglasses | B2915: DressBerry | C2915: 3.8 | D2915: 330 | E2915: 1599 | F2915: 719 | G2915: L | H2915: sunglasses | I2915: 5595600 | J2915: =D2915*F2915 -> 237270 | K2915: =((Table4[[#This Row],[marked_price]]-Table4[[#This Row],[discounted_price]])/Table4[[#This Row],[marked_price]])*100 -> 55.034396
A2916: Women Crystal Studded Brooch | B2916: Yellow Chimes | C2916: 5 | D2916: 6 | E2916: 1082 | F2916: 437 | G2916: Onesize | H2916: brooch | I2916: 17015884 | J2916: =D2916*F2916 -> 2622 | K2916: =((Table4[[#This Row],[marked_price]]-Table4[[#This Row],[discounted_price]])/Table4[[#This Row],[marked_price]])*100 -> 59.61183
A2917: Regular Fit Casual Shirt | B2917: Pepe Jeans | C2917: 4.6 | D2917: 20 | E2917: 2199 | F2917: 879 | G2917: S,M,L,XL | H2917: shirts | I2917: 12513566 | J2917: =D2917*F2917 -> 17580 | K2917: =((Table4[[#This Row],[marked_price]]-Table4[[#This Row],[discounted_price]])/Table4[[#This Row],[marked_price]])*100 -> 60.027285
A2918: EDGE Men Track Pants | B2918: HRX by Hrithik Roshan | C2918: 4 | D2918: 23 | E2918: 2999 | F2918: 1799 | G2918: S,M,L,XL,XXL | H2918: track-pants | I2918: 14646054 | J2918: =D2918*F2918 -> 41377 | K2918: =((Table4[[#This Row],[marked_price]]-Table4[[#This Row],[discounted_price]])/Table4[[#This Row],[marked_price]])*100 -> 40.013338
A2919: Women Mules Flats | B2919: DEAS | C2919: 4.3 | D2919: 133 | E2919: 999 | F2919: 599 | G2919: EURO36,EURO37,EURO38,EURO39,EURO40,EURO41,EURO42 | H2919: flats | I2919: 14869308 | J2919: =D2919*F2919 -> 79667 | K2919: =((Table4[[#This Row],[marked_price]]-Table4[[#This Row],[discounted_price]])/Table4[[#This Row],[marked_price]])*100 -> 40.04004
A2920: 144 TC 1 King Bedsheet with 2 Pillow Covers | B2920: Rajasthan Decor | C2920: 4.3 | D2920: 408 | E2920: 1999 | F2920: 939 | G2920: Double King | H2920: bedsheets | I2920: 4320535 | J2920: =D2920*F2920 -> 383112 | K2920: =((Table4[[#This Row],[marked_price]]-Table4[[#This Row],[discounted_price]])/Table4[[#This Row],[marked_price]])*100 -> 53.026513
... A3039: Women Embroidered Kurta with Churidar With Dupatta | B3039: Ziva Fashion | C3039: 4.2 | D3039: 16 | E3039: 2999 | F3039: 1499 | G3039: S,M,L,XL,XXL | H3039: kurta-sets | I3039: 17972212 | J3039: =D3039*F3039 -> 23984 | K3039: =((Table4[[#This Row],[marked_price]]-Table4[[#This Row],[discounted_price]])/Table4[[#This Row],[marked_price]])*100 -> 50.016672
A3040: Regular Fit Casual Shirt | B3040: Louis Philippe Jeans | C3040: 4.3 | D3040: 28 | E3040: 2049 | F3040: 1229 | G3040: 44 | H3040: shirts | I3040: 12848626 | J3040: =D3040*F3040 -> 34412 | K3040: =((Table4[[#This Row],[marked_price]]-Table4[[#This Row],[discounted_price]])/Table4[[#This Row],[marked_price]])*100 -> 40.019522
A3041: Women Sequinned Saree Blouse | B3041: Inddus | C3041: 3.5 | D3041: 8 | E3041: 1999 | F3041: 859 | G3041: Onesize | H3041: saree-blouse | I3041: 17535092 | J3041: =D3041*F3041 -> 6872 | K3041: =((Table4[[#This Row],[marked_price]]-Table4[[#This Row],[discounted_price]])/Table4[[#This Row],[marked_price]])*100 -> 57.028514
A3042: Slim Checked Shirt | B3042: The Indian Garage Co | C3042: 4.1 | D3042: 19 | E3042: 1749 | F3042: 699 | G3042: 38,40,42,44,46 | H3042: shirts | I3042: 12182240 | J3042: =D3042*F3042 -> 13281 | K3042: =((Table4[[#This Row],[marked_price]]-Table4[[#This Row],[discounted_price]])/Table4[[#This Row],[marked_price]])*100 -> 60.034305
A3043: Colourblocked Satin Top | B3043: STREET 9 | C3043: 3.9 | D3043: 34 | E3043: 1599 | F3043: 607 | G3043: XS,S,M,L | H3043: tops | I3043: 15884818 | J3043: =D3043*F3043 -> 20638 | K3043: =((Table4[[#This Row],[marked_price]]-Table4[[#This Row],[discounted_price]])/Table4[[#This Row],[marked_price]])*100 -> 62.038774
A3044: Men Slim Fit T-shirt | B3044: Flying Machine | C3044: 4.9 | D3044: 7 | E3044: 1099 | F3044: 989 | G3044: S,M,L,XL,XXL | H3044: tshirts | I3044: 16746312 | J3044: =D3044*F3044 -> 6923 | K3044: =((Table4[[#This Row],[marked_price]]-Table4[[#This Row],[discounted_price]])/Table4[[#This Row],[marked_price]])*100 -> 10.009099
A3045: Men Solid Biker Jacket | B3045: The Indian Garage Co | C3045: 4.2 | D3045: 50 | E3045: 6299 | F3045: 2519 | G3045: M,L,XL,XXL | H3045: jackets | I3045: 7272191 | J3045: =D3045*F3045 -> 125950 | K3045: =((Table4[[#This Row],[marked_price]]-Table4[[#This Row],[discounted_price]])/Table4[[#This Row],[marked_price]])*100 -> 60.009525
A3046: Kids Set of Bodywash & Shampoo | B3046: Mamaearth | C3046: 4.5 | D3046: 1000 | E3046: 798 | F3046: 678 | G3046: Pack | H3046: body-wash-and-scrub | I3046: 13566986 | J3046: =D3046*F3046 -> 678000 | K3046: =((Table4[[#This Row],[marked_price]]-Table4[[#This Row],[discounted_price]])/Table4[[#This Row],[marked_price]])*100 -> 15.037594
A3047: 144 TC 1 King Bedsheet with 2 Pillow Covers | B3047: Florida | C3047: 3.8 | D3047: 235 | E3047: 1299 | F3047: 467 | G3047: Double King | H3047: bedsheets | I3047: 13782486 | J3047: =D3047*F3047 -> 109745 | K3047: =((Table4[[#This Row],[marked_price]]-Table4[[#This Row],[discounted_price]])/Table4[[#This Row],[marked_price]])*100 -> 64.049269
A3048: Women Running Shoes | B3048: Campus | C3048: 2.5 | D3048: 2 | E3048: 1799 | F3048: 1574 | G3048: UK4,UK5,UK6,UK7,UK8 | H3048: sports-shoes | I3048: 16807270 | J3048: =D3048*F3048 -> 3148 | K3048: =((Table4[[#This Row],[marked_price]]-Table4[[#This Row],[discounted_price]])/Table4[[#This Row],[marked_price]])*100 -> 12.506948
A3049: Men Leather Textured Belt | B3049: Tommy Hilfiger | C3049: 4.1 | D3049: 24 | E3049: 2899 | F3049: 1884 | G3049: 44 | H3049: belts | I3049: 9146085 | J3049: =D3049*F3049 -> 45216 | K3049: =((Table4[[#This Row],[marked_price]]-Table4[[#This Row],[discounted_price]])/Table4[[#This Row],[marked_price]])*100 -> 35.012073
A3050: Solid One-Shoulder Dress | B3050: Inddus | C3050: 4.2 | D3050: 16 | E3050: 5899 | F3050: 2477 | G3050: XS,S,M,L,XL,XXL | H3050: dresses | I3050: 15916416 | J3050: =D3050*F3050 -> 39632 | K3050: =((Table4[[#This Row],[marked_price]]-Table4[[#This Row],[discounted_price]])/Table4[[#This Row],[marked_price]])*100 -> 58.009832
A3051: HRX-U-17 Active T-shirt | B3051: HRX by Hrithik Roshan | C3051: 4.8 | D3051: 13 | E3051: 1199 | F3051: 1199 | G3051: 8-9Y,10-11Y,12-13Y,14-15Y,16-17Y | H3051: tshirts | I3051: 14701892 | J3051: =D3051*F3051 -> 15587 | K3051: =((Table4[[#This Row],[marked_price]]-Table4[[#This Row],[discounted_price]])/Table4[[#This Row],[marked_price]])*100 -> 0
A3052: Women Empire Midi Dress | B3052: IMARA | C3052: 3.9 | D3052: 10 | E3052: 1999 | F3052: 999 | G3052: S,M,L,XL,XXL | H3052: dresses | I3052: 15271626 | J3052: =D3052*F3052 -> 9990 | K3052: =((Table4[[#This Row],[marked_price]]-Table4[[#This Row],[discounted_price]])/Table4[[#This Row],[marked_price]])*100 -> 50.025013
A3053: Women Pink Sandals | B3053: ZAPATOZ | C3053: 3.8 | D3053: 26 | E3053: 999 | F3053: 849 | G3053: EURO36,EURO37,EURO38,EURO39,EURO40,EURO41 | H3053: heels | I3053: 14961996 | J3053: =D3053*F3053 -> 22074 | K3053: =((Table4[[#This Row],[marked_price]]-Table4[[#This Row],[discounted_price]])/Table4[[#This Row],[marked_price]])*100 -> 15.015015
A3054: Women Printed Kurta with Palazzos With Dupatta | B3054: GERUA | C3054: 4.6 | D3054: 9 | E3054: 2999 | F3054: 1499 | G3054: XS,S,M,L,XL,XXL | H3054: kurta-sets | I3054: 17627614 | J3054: =D3054*F3054 -> 13491 | K3054: =((Table4[[#This Row],[marked_price]]-Table4[[#This Row],[discounted_price]])/Table4[[#This Row],[marked_price]])*100 -> 50.016672
A3055: Solid Twisted Crop Top | B3055: Roadster | C3055: 3.4 | D3055: 5 | E3055: 999 | F3055: 399 | G3055: XS,S,M,L,XL | H3055: tops | I3055: 16961238 | J3055: =D3055*F3055 -> 1995 | K3055: =((Table4[[#This Row],[marked_price]]-Table4[[#This Row],[discounted_price]])/Table4[[#This Row],[marked_price]])*100 -> 60.06006
...

Sheet brand_pivot
C2: BRAND PIVOT
C4: Row Labels | D4: Average of marked_price | E4: Average of discounted_price | G4: Row Labels | H4: Average of rating | J4: Row Labels | K4: Sum of rating_count | M4: Row Labels | N4: Sum of revenue | P4: Row Labels | Q4: Count of product_category
C5: ADIDAS | D5: 2844.4545 | E5: 2265.3636 | G5: ADIDAS | H5: 4.3636364 | J5: ADIDAS | K5: 759 | M5: ADIDAS | N5: 897081 | P5: ADIDAS | Q5: 11
C6: Allen Solly | D6: 2370.7143 | E6: 1776.7 | G6: Allen Solly | H6: 4.3285714 | J6: Allen Solly | K6: 2833 | M6: Allen Solly | N6: 3905605 | P6: Allen Solly | Q6: 70
C7: Nike | D7: 2895 | E7: 2796.2308 | G7: Nike | H7: 4.4307692 | J7: Nike | K7: 306 | M7: Nike | N7: 766322 | P7: Nike | Q7: 13
C8: Puma | D8: 2991.9825 | E8: 1819.5263 | G8: Puma | H8: 4.2640351 | J8: Puma | K8: 3326 | M8: Puma | N8: 5564869 | P8: Puma | Q8: 114
C9: Grand Total | D9: 2769.0385 | E9: 1889.7356 | G9: Grand Total | H9: 4.3014423 | J9: Grand Total | K9: 7224 | M9: Grand Total | N9: 11133877 | P9: Grand Total | Q9: 208

Sheet brand_dashboard
C2: BRAND DASHBOARD

Sheet product_pivot
B2: PRODUCT PIVOT
B5: Row Labels | C5: Avg of discounted_price | D5: Aveg of marked_price | F5: Row Labels | G5: Sum of rating_count | I5: Row Labels | J5: Count of brand_name
B6: action-figures-and-play-set | C6: 591 | D6: 799 | F6: action-figures-and-play-set | G6: 9 | I6: action-figures-and-play-set | J6: 1
B7: baby-care-products | C7: 344 | D7: 349 | F7: baby-care-products | G7: 932 | I7: baby-care-products | J7: 3
B8: track-pants | C8: 1099.2143 | D8: 1953 | F8: track-pants | G8: 17942 | I8: track-pants | J8: 252
B9: tshirts | C9: 677.15254 | D9: 1207.0473 | F9: tshirts | G9: 94149 | I9: tshirts | J9: 1121
B10: Grand Total | C10: 753.60421 | D10: 1341.3958 | F10: Grand Total | G10: 113032 | I10: Grand Total | J10: 1377

Sheet product_dashboard
C3: PRODUCT DASHBOARD

Sheet Overall_Dashboard
E3: Overall Dashboard
G6: Total products | H6: Total brands | I6: Total categories | J6: Total people | K6: Total rating
E7: Raw data | G7: =COUNTA([1]V1!$A$2:$A$24325) -> 24324 | H7: =COUNTA([1]V1!$B$1:$B$24325) -> 24325 | I7: =COUNTA([1]V2!$I$5:$I$21605) -> 21601 | J7: =SUM([1]V1!$D$1:$D$21605) -> 1247767 | K7: =AVERAGE([1]V1!$C$2:$C$24325) -> 2.1832264
E9: Cleaned data | G9: =COUNTA(Cleaned_data!A2:A11439) -> 11438 | H9: =COUNTA(_xlfn.UNIQUE(Cleaned_data!B2:B11439)) -> 1458 | I9: =COUNTA(_xlfn.UNIQUE(Cleaned_data!H2:H11439)) -> 245 | J9: =SUM(Cleaned_data!D2:D11439) -> 1404665 | K9: =AVERAGE(Cleaned_data!C2:C11439) -> 4.1597744

Sheet LinkedIn_Dashboard
A1: MYNTRA PRODUCT DATA ANALYSIS
A2: Cleaned dataset insights • 11,438 unique products • Top 5 performance analysis
A3: TOTAL PRODUCTS | E3: TOTAL BRANDS | I3: CATEGORIES | M3: RATING VOLUME | Q3: AVG. RATING | U3: ENGAGEMENT VALUE
A4: =Overall_Dashboard!G9 -> 11438 | E4: =Overall_Dashboard!H9 -> 1458 | I4: =Overall_Dashboard!I9 -> 245 | M4: =Overall_Dashboard!J9 -> 1404665 | Q4: =Overall_Dashboard!K9 -> 4.1597744 | U4: =SUM(Cleaned_data!J2:J11439) -> 1281237476
A6: Brand & Category Performance
A37: TOP BRAND Roadster leads with 80,847 ratings. | I37: TOP CATEGORY Perfume & Body Mist dominates with 125,303 ratings. | Q37: RATING LEADER MCaffeine scores 4.61, highest among the Top 5 brands.
A40: Created by Madhavareddy Erugula | Excel • Data Cleaning • Pivot Tables • Dashboarding
A45: Brand | B45: Avg Marked Price | C45: Avg Discounted Price | D45: Brand | E45: Avg Rating | F45: Brand | G45: Rating Count | H45: Brand | I45: Engagement Value | J45: Brand | K45: Product Count | L45: Category | M45: Avg Marked Price | N45: Avg Discounted Price | O45: Category | P45: Rating Count | Q45: Category | R45: Product Count
A46: Roadster | B46: 1768.1947 | C46: 782.11062 | D46: Roadster | E46: 4.1309735 | F46: Roadster | G46: 80847 | H46: Roadster | I46: 59111098 | J46: Roadster | K46: 452 | L46: Perfume And Body Mist | M46: 2723.8 | N46: 2382.75 | O46: Perfume And Body Mist | P46: 125303 | Q46: Perfume And Body Mist | R46: 100
A47: DressBerry | B47: 1896.4356 | C47: 803.83556 | D47: DressBerry | E47: 4.2102222 | F47: DressBerry | G47: 71240 | H47: DressBerry | I47: 48535395 | J47: DressBerry | K47: 225 | L47: T-Shirts | M47: 1207.0473 | N47: 677.15254 | O47: T-Shirts | P47: 94149 | Q47: T-Shirts | R47: 1121
A48: Plum | B48: 665.71429 | C48: 535.5 | D48: Plum | E48: 4.4 | F48: Plum | G48: 65603 | H48: Plum | I48: 56575241 | J48: Plum | K48: 14 | L48: Tops | M48: 1423.6266 | N48: 740.82143 | O48: Tops | P48: 59387 | Q48: Tops | R48: 616
A49: Lakme | B49: 516.91667 | C49: 471.29167 | D49: Lakme | E49: 4.3791667 | F49: Lakme | G49: 51360 | H49: Lakme | I49: 32333287 | J49: Lakme | K49: 24 | L49: Kurtas | M49: 2168.9098 | N49: 946.23333 | O49: Kurtas | P49: 52705 | Q49: Kurtas | R49: 510
A50: MCaffeine | B50: 716.2 | C50: 625.1 | D50: MCaffeine | E50: 4.61 | F50: MCaffeine | G50: 42789 | H50: MCaffeine | I50: 38870147 | J50: MCaffeine | K50: 10 | L50: Dresses | M50: 2482.7915 | N50: 1249.0352 | O50: Dresses | P50: 51634 | Q50: Dresses | R50: 710
